django_prosemirror-0.0.12.dist-info/DESCRIPTION.rst
django_prosemirror-0.0.12.dist-info/METADATA
django_prosemirror-0.0.12.dist-info/RECORD
django_prosemirror-0.0.12.dist-info/WHEEL
django_prosemirror-0.0.12.dist-info/metadata.json
django_prosemirror-0.0.12.dist-info/top_level.txt
prosemirror/__init__.py
prosemirror/_version.py
prosemirror/fields.py
prosemirror/steakmark.py
prosemirror/widgets.py
prosemirror/static/prosemirror/maxi-spec.js
prosemirror/static/prosemirror/micro-spec.js
prosemirror/static/prosemirror/widget.js
prosemirror/static/prosemirror/widget.min.css
prosemirror/static/prosemirror/widget.min.js
prosemirror/static/prosemirror/widget.scss
prosemirror/templatetags/__init__.py
prosemirror/templatetags/prosemirror.py
