Metadata-Version: 2.0
Name: django-prosemirror
Version: 0.0.12
Summary: Prosemirror field for django
Home-page: https://github.com/zakdoek/django-prosemirror/
Author: Tom Van Damme
Author-email: t_o_mvandamme@hotmail.com
License: MIT
Platform: UNKNOWN
Classifier: Framework :: Django
Requires-Dist: commonmark (>=0.7.0)
